pycui_utils/__init__.py
pycui_utils/py.typed
pycui_utils/databases/__init__.py
pycui_utils/databases/cui.json
pycui_utils/tests/__init__.py
pycui_utils/tests/test_general.py
pycui_utils-0.3.0.dist-info/METADATA
pycui_utils-0.3.0.dist-info/WHEEL
pycui_utils-0.3.0.dist-info/entry_points.txt
pycui_utils-0.3.0.dist-info/RECORD
