Metadata-Version: 2.4
Name: pycui-utils
Version: 0.3.0
Summary: Python library for managing Controlled Unclassified Information (CUI) categories and their metadata.
Project-URL: Repository, https://github.com/brehldev/pycui-utils
Project-URL: Homepage, https://github.com/brehldev/pycui-utils
Project-URL: Documentation, https://www.archives.gov/cui
License-Expression: MIT
Keywords: Executive Order 13526,NARA,classification,compliance,controlled unclassified information,cui,government,information security,security
Requires-Python: >=3.9
